sfx7z/__init__.py
sfx7z/core.py
sfx7z/utils.py
sfx7z/__metadata__/DISCLIAIMER.md
sfx7z/__metadata__/LICENSE
sfx7z/__metadata__/README.md
sfx7z/__metadata__/__init__.py
sfx7z/__metadata__/requirements.txt
sfx7z/pkg_data/7z.sfx
sfx7z/pkg_data/7zCon.sfx
sfx7z/pkg_data/7zS.sfx
sfx7z/pkg_data/7zSD.sfx
sfx7z-0.2.0.dist-info/METADATA
sfx7z-0.2.0.dist-info/WHEEL
sfx7z-0.2.0.dist-info/top_level.txt
sfx7z-0.2.0.dist-info/RECORD
