Metadata-Version: 2.1
Name: sfx7z
Version: 0.2.0
Summary: py7zr wrapper with SFX options.
Home-page: http://code.foxe6.kozow.com/sfx7z/
Author: f̣ộx̣ệ6
Author-email: foxe6@pm.me
License: AGPL-3.0
Project-URL: Sourcecode, http://code.foxe6.kozow.com/sfx7z.zip
Project-URL: Documentation, http://code.foxe6.kozow.com/sfx7z/docs/
Project-URL: Example, http://code.foxe6.kozow.com/sfx7z/test/
Project-URL: Funding, https://paypal.me/foxe6
Project-URL: Say Thanks!, https://saythanks.io/to/foxe6
Keywords: 7z 7zip sfx file archive self extract multi volume split join
Platform: UNKNOWN
Classifier: Programming Language :: Python :: 3.9
Classifier: Topic :: Utilities
Classifier: Natural Language :: English
Classifier: Intended Audience :: Developers
Classifier: License :: OSI Approved :: GNU Affero General Public License v3
Classifier: Operating System :: MacOS
Classifier: Operating System :: POSIX
Classifier: Operating System :: Microsoft :: Windows :: Windows 10
Classifier: Development Status :: 5 - Production/Stable
Requires-Python: >=3.5
Requires-Dist: py7zr (>=0.0.1)
Requires-Dist: multivolumefile (>=0.0.1)
